[
  {
    "slug": "madhesh-mahasabha-formation-announcement",
    "title": "Madhesh Mahasabha Formation Announcement",
    "titleNp": "मधेश महासभा गठन घोषणा",
    "content": "We are pleased to announce the official formation of Madhesh Mahasabha, a new political organization dedicated to the unity, equality, and rights of Madhesh and Madheshi people...",
    "contentNp": "मधेश र मधेशीको एकता, समानता र अधिकारका लागि समर्पित नयाँ राजनीतिक संगठन 'मधेश महासभा' को आज औपचारिक रूपमा गठन भएको घोषणा गरिएको छ।\n\nमधेश महासभाको मूल उद्देश्य मधेश र मधेशी समुदायको हक, हित र अधिकारको संरक्षण गर्नुका साथै देशको समग्र विकासमा योगदान पुर्‍याउनु हो।\n\nमुख्य बुँदाहरू:\n\n१. समान प्रतिनिधित्व: संघीय, प्रादेशिक र स्थानीय तहमा मधेशीहरूको समान प्रतिनिधित्व सुनिश्चित गर्ने\n\n२. आर्थिक विकास: मधेश प्रदेशको समग्र आर्थिक विकास र समृद्धिका लागि योजना निर्माण\n\n३. सामाजिक न्याय: समाजमा विद्यमान भेदभाव र असमानता उन्मूलन गर्दै सामाजिक न्याय स्थापना\n\n४. सांस्कृतिक संरक्षण: मधेशी संस्कृति, भाषा र परम्पराको संरक्षण र प्रवर्द्धन",
    "excerpt": "Official announcement of the formation of Madhesh Mahasabha, a new political organization.",
    "excerptNp": "मधेश महासभाको गठनको आधिकारिक घोषणा। नयाँ संगठनको उद्देश्य र कार्यदिशाको विस्तृत जानकारी।",
    "category": "announcement",
    "tags": ["गठन", "घोषणा", "संगठन", "राजनीति"],
    "priority": "urgent",
    "author": "मधेश महासभा केन्द्रीय समिति",
    "contactEmail": "mahasabhamadhesh@gmail.com",
    "isPublished": true
  },
  {
    "slug": "equal-representation-statement",
    "title": "Statement on Equal Representation",
    "titleNp": "समान प्रतिनिधित्वको विषयमा वक्तव्य",
    "content": "Madhesh Mahasabha demands equal representation at all levels of government...",
    "contentNp": "मधेश महासभाले सरकारका सबै तहमा समान प्रतिनिधित्वको माग गरेको छ।\n\nहामी विश्वास गर्छौं कि लोकतन्त्रको वास्तविक अर्थ सबै समुदायको समानुपातिक र समावेशी प्रतिनिधित्व हो।\n\nमधेश प्रदेशमा बसोबास गर्ने जनताको संख्या र योगदानको आधारमा संघीय संरचनामा उचित प्रतिनिधित्व हुनुपर्छ।",
    "excerpt": "Madhesh Mahasabha's official statement on equal representation.",
    "excerptNp": "समान प्रतिनिधित्वको माग गर्दै मधेश महासभाको आधिकारिक वक्तव्य।",
    "category": "statement",
    "tags": ["प्रतिनिधित्व", "समानता", "लोकतन्त्र"],
    "priority": "high",
    "author": "मधेश महासभा प्रवक्ता",
    "contactEmail": "mahasabhamadhesh@gmail.com",
    "isPublished": true
  },
  {
    "slug": "cultural-festival-2081",
    "title": "Madhesh Cultural Festival 2081",
    "titleNp": "मधेश सांस्कृतिक महोत्सव २०८१",
    "content": "Join us for the grand Madhesh Cultural Festival 2081...",
    "contentNp": "मधेश महासभाले आयोजना गर्न लागेको मधेश सांस्कृतिक महोत्सव २०८१ मा सबैलाई स्वागत छ।\n\nयस महोत्सवमा मधेशी संस्कृति, कला, साहित्य र परम्पराको प्रदर्शन गरिनेछ।\n\nकार्यक्रम विवरण:\nमिति: २०८१ माघ १५ गते\nस्थान: जनकपुर, मधेश प्रदेश\nसमय: बिहान १० बजे देखि\n\nविशेष आकर्षणहरू:\n- परम्परागत नृत्य र संगीत\n- मैथिली र भोजपुरी साहित्य\n- स्थानीय खानेकुरा महोत्सव\n- कला प्रदर्शनी",
    "excerpt": "Grand cultural festival celebrating Madheshi culture and traditions.",
    "excerptNp": "मधेशी संस्कृति र परम्पराको उत्सव मनाउने भव्य सांस्कृतिक महोत्सव।",
    "category": "event",
    "tags": ["संस्कृति", "महोत्सव", "कार्यक्रम", "जनकपुर"],
    "priority": "normal",
    "author": "मधेश महासभा सांस्कृतिक समिति",
    "contactEmail": "mahasabhamadhesh@gmail.com",
    "contactPhone": "+977-41-XXXXXX",
    "isPublished": true
  },
  {
    "slug": "youth-empowerment-achievement",
    "title": "Youth Empowerment Program Success",
    "titleNp": "युवा सशक्तिकरण कार्यक्रमको सफलता",
    "content": "Our youth empowerment program has successfully trained 500+ youth...",
    "contentNp": "मधेश महासभाको युवा सशक्तिकरण कार्यक्रमले ५०० भन्दा बढी युवाहरूलाई सफलतापूर्वक तालिम प्रदान गरेको छ।\n\nयो कार्यक्रममा युवाहरूलाई:\n- नेतृत्व विकास तालिम\n- कौशल विकास कार्यक्रम\n- उद्यमशीलता प्रशिक्षण\n- सामाजिक सेवाको अवसर\n\nप्रदान गरिएको थियो।\n\nयस कार्यक्रमबाट स्नातक भएका युवाहरूमध्ये ७०% ले आफ्नो व्यवसाय सुरु गरेका वा रोजगारी पाएका छन्।",
    "excerpt": "500+ youth successfully trained through our empowerment program.",
    "excerptNp": "हाम्रो सशक्तिकरण कार्यक्रमबाट ५००+ युवाहरू सफलतापूर्वक तालिम प्राप्त।",
    "category": "achievement",
    "tags": ["युवा", "सशक्तिकरण", "तालिम", "उपलब्धि"],
    "priority": "normal",
    "author": "मधेश महासभा युवा समिति",
    "contactEmail": "youth@mahasabhamadhesh.org",
    "isPublished": true
  }
]
